LICENSE
MANIFEST.in
NOTICE
README.md
pyproject.toml
setup.py
ciderpress/__init__.py
ciderpress.egg-info/PKG-INFO
ciderpress.egg-info/SOURCES.txt
ciderpress.egg-info/dependency_links.txt
ciderpress.egg-info/requires.txt
ciderpress.egg-info/top_level.txt
ciderpress/data/__init__.py
ciderpress/data/expnt_maxs.npy
ciderpress/data/expnt_mins.npy
ciderpress/dft/__init__.py
ciderpress/dft/baselines.py
ciderpress/dft/debug_numint.py
ciderpress/dft/density_util.py
ciderpress/dft/feat_normalizer.py
ciderpress/dft/grids_indexer.py
ciderpress/dft/lcao_convolutions.py
ciderpress/dft/lcao_interpolation.py
ciderpress/dft/lcao_nldf_generator.py
ciderpress/dft/model_utils.py
ciderpress/dft/plans.py
ciderpress/dft/pwutil.py
ciderpress/dft/settings.py
ciderpress/dft/sph_harm_coeff.py
ciderpress/dft/transform_data.py
ciderpress/dft/xc_evaluator.py
ciderpress/dft/xc_evaluator2.py
ciderpress/dft/xc_torch.py
ciderpress/external/__init__.py
ciderpress/external/sgx_tools.py
ciderpress/gpaw/__init__.py
ciderpress/gpaw/atom_descriptor_utils.py
ciderpress/gpaw/atom_utils.py
ciderpress/gpaw/calculator.py
ciderpress/gpaw/cider_fft.py
ciderpress/gpaw/cider_kernel.py
ciderpress/gpaw/cider_paw.py
ciderpress/gpaw/cider_sl.py
ciderpress/gpaw/config.py
ciderpress/gpaw/descriptors.py
ciderpress/gpaw/fit_paw_gauss_pot.py
ciderpress/gpaw/gpaw_grids.py
ciderpress/gpaw/interp_paw.py
ciderpress/gpaw/nldf_interface.py
ciderpress/gpaw/xc_tools.py
ciderpress/lib/CMakeLists.txt
ciderpress/lib/__init__.py
ciderpress/lib/fft_plan.py
ciderpress/lib/load.py
ciderpress/lib/mpi_fft_plan.py
ciderpress/lib/fft_wrapper/CMakeLists.txt
ciderpress/lib/fft_wrapper/cider_fft.c
ciderpress/lib/fft_wrapper/cider_fft.h
ciderpress/lib/fft_wrapper/cider_mpi_fft.c
ciderpress/lib/fft_wrapper/cider_mpi_fft.h
ciderpress/lib/fft_wrapper/config.h.in
ciderpress/lib/mod_cider/CMakeLists.txt
ciderpress/lib/mod_cider/cider_coefs.c
ciderpress/lib/mod_cider/cider_grids.c
ciderpress/lib/mod_cider/conv_interpolation.c
ciderpress/lib/mod_cider/conv_interpolation.h
ciderpress/lib/mod_cider/convolutions.c
ciderpress/lib/mod_cider/convolutions.h
ciderpress/lib/mod_cider/debug_numint.c
