Metadata-Version: 2.2
Name: ciderpress
Version: 0.4.0
Summary: CiderPress: DFT Calculations with Machine-Learned XC Functionals
Author-email: Kyle Bystrom <kylebystrom@gmail.com>
Maintainer-email: Kyle Bystrom <kylebystrom@gmail.com>
Project-URL: Repository, https://github.com/mir-group/CiderPress
Classifier: Development Status :: 3 - Alpha
Classifier: Intended Audience :: Science/Research
Classifier: Intended Audience :: Developers
Classifier: Programming Language :: C
Classifier: Programming Language :: Python
Classifier: Topic :: Scientific/Engineering
Classifier: Operating System :: POSIX
Classifier: Operating System :: Unix
License-File: LICENSE
License-File: NOTICE
Requires-Dist: ase>=3.22.0
Requires-Dist: h5py>=3.6.0
Requires-Dist: interpolation>=2.2.7
Requires-Dist: numba>=0.60
Requires-Dist: numpy>=1.20
Requires-Dist: pyscf>=2.6
Requires-Dist: pytest
Requires-Dist: pyyaml
Requires-Dist: scikit-learn>=1.0.1
Requires-Dist: scipy>=1.12
Requires-Dist: sympy
